{"cache_date": "2024-07-18", "page_authors": {"docs/index.md": {"last_commit_date": "2023-11-18", "authors": [{"login": "AzurIce", "name": "AzurIce", "url": "https://github.com/AzurIce", "avatar": "https://avatars.githubusercontent.com/u/22115534?v=4"}]}, "docs/blog/index.md": {"last_commit_date": "2023-08-14", "authors": []}, "docs/blog/posts/-WSL \u2014\u2014 \u5728Windows \u4e2d\u4f7f\u7528 Linux \u7cfb\u7edf.md": {"last_commit_date": "2023-11-30", "authors": []}, "docs/blog/posts/Github Actions \u5168\u6307\u5357.md": {"last_commit_date": "2023-10-17", "authors": []}, "docs/blog/posts/KMP \u7b97\u6cd5 \u2014\u2014 \u524d\u7f00\u51fd\u6570\uff08\u524d\u7f00\u6570\u7ec4\uff09.md": {"last_commit_date": "2023-08-14", "authors": []}, "docs/blog/posts/blog.md": {"last_commit_date": "2023-08-20", "authors": []}, "docs/blog/posts/mermaid \u7518\u7279\u56fe\u6e32\u67d3\u8fc7\u5c0f\u8e29\u5751\u8bb0\u5f55.md": {"last_commit_date": "2023-11-30", "authors": []}, "docs/blog/posts/old test.md": {"last_commit_date": "2023-08-15", "authors": []}, "docs/blog/posts/\u4f7f\u7528 OhMyPosh \u7f8e\u5316 PowerShell.md": {"last_commit_date": "2023-11-30", "authors": []}, "docs/blog/posts/\u4f7f\u7528 clog-cli \u7531 git commit \u751f\u6210 changelog.md": {"last_commit_date": "2023-11-30", "authors": []}, "docs/blog/posts/\u4f7f\u7528\u54c8\u5e0c\u7b97\u6cd5\u4ee5\u53ca\u52a0\u76d0\u6765\u589e\u5f3a\u670d\u52a1\u7aef\u5bc6\u7801\u5b58\u50a8\u5b89\u5168.md": {"last_commit_date": "2023-08-14", "authors": []}, "docs/blog/posts/\u4fee\u6539 VSCode UI \u754c\u9762\u5b57\u4f53.md": {"last_commit_date": "2023-11-30", "authors": []}, "docs/blog/posts/\u544a\u522b\u7e41\u7410\u5b89\u88c5\u754c\u9762\uff0c\u4f7f\u7528Scoop\u7ba1\u7406Windows\u8f6f\u4ef6.md": {"last_commit_date": "2023-11-30", "authors": []}, "docs/blog/posts/\u5927\u6570\u636e\u534e\u4e3a\u4e91\u5b9e\u8df5\u4f5c\u4e1a\u8e29\u5751\u8bb0\u5f55\uff08\u5b9e\u9a8c\u62a5\u544a.md": {"last_commit_date": "2023-11-30", "authors": []}, "docs/blog/posts/\u63d0\u9ad8\u751f\u4ea7\u529b\u7684\u5de5\u5177\u4eec\uff08\u6301\u7eed\u66f4\u65b0\uff09.md": {"last_commit_date": "2023-11-30", "authors": []}, "docs/blog/posts/\u7528 Markdown \u4ee3\u66ff ppt \u2014\u2014 \u4f7f\u7528 Slidev \u5236\u4f5c\u6f14\u793a\u6587\u7a3f.md": {"last_commit_date": "2023-11-30", "authors": []}, "docs/blog/posts/\u8bb0\u4e00\u6b21Typecho\u535a\u5ba2\u90e8\u7f72.md": {"last_commit_date": "2023-08-14", "authors": []}, "docs/blog/posts/Coding/C\u3001C++/C\u8bed\u8a00\u6559\u7a0b/\u300eC\u8bed\u8a00\u6559\u7a0b\u300f0. \u8e0f\u5165C\u7684\u5927\u95e8.md": {"last_commit_date": "2023-08-20", "authors": []}, "docs/blog/posts/Coding/C\u3001C++/C\u8bed\u8a00\u6559\u7a0b/\u300eC\u8bed\u8a00\u6559\u7a0b\u300f1. \u53d8\u91cf\u3001\u8f93\u5165\u8f93\u51fa.md": {"last_commit_date": "2023-08-20", "authors": []}, "docs/blog/posts/Coding/C\u3001C++/C\u8bed\u8a00\u6559\u7a0b/\u300eC\u8bed\u8a00\u6559\u7a0b\u300f2. \u5206\u652f\u7ed3\u6784.md": {"last_commit_date": "2023-08-20", "authors": []}, "docs/blog/posts/Coding/C\u3001C++/C\u8bed\u8a00\u6559\u7a0b/\u300eC\u8bed\u8a00\u6559\u7a0b\u300f3. \u5faa\u73af\u7ed3\u6784.md": {"last_commit_date": "2023-08-20", "authors": []}, "docs/blog/posts/Coding/C\u3001C++/C\u8bed\u8a00\u6559\u7a0b/\u300eC\u8bed\u8a00\u6559\u7a0b\u300f4. \u51fd\u6570.md": {"last_commit_date": "2023-08-20", "authors": []}, "docs/blog/posts/Coding/C\u3001C++/C\u8bed\u8a00\u6559\u7a0b/\u300eC\u8bed\u8a00\u6559\u7a0b\u300f5. \u6307\u9488.md": {"last_commit_date": "2023-08-20", "authors": []}, "docs/blog/posts/Coding/C\u3001C++/C\u8bed\u8a00\u6559\u7a0b/\u300eC\u8bed\u8a00\u6559\u7a0b\u300f6. \u6570\u7ec4\u4e0e\u5b57\u7b26\u4e32.md": {"last_commit_date": "2023-08-20", "authors": []}, "docs/blog/posts/Coding/C\u3001C++/C\u8bed\u8a00\u6559\u7a0b/\u300eC\u8bed\u8a00\u6559\u7a0b\u300f7. \u6587\u4ef6.md": {"last_commit_date": "2023-12-07", "authors": []}, "docs/blog/posts/Coding/Golang/GORM \u6e90\u7801\u9605\u8bfb.md": {"last_commit_date": "2023-08-20", "authors": []}, "docs/blog/posts/Coding/Golang/Golang \u63a5\u53e3.md": {"last_commit_date": "2023-08-20", "authors": []}, "docs/blog/posts/Coding/Golang/Golang \u6587\u6863\u6ce8\u91ca.md": {"last_commit_date": "2023-08-20", "authors": []}, "docs/blog/posts/Coding/Golang/Golang \u6807\u51c6\u5e93\u4e4b context.md": {"last_commit_date": "2023-08-20", "authors": []}, "docs/blog/posts/Coding/Golang/Golang \u6807\u51c6\u5e93\u4e4b sql.md": {"last_commit_date": "2023-08-20", "authors": []}, "docs/blog/posts/Coding/Java/\u300e\u4eceC\u5230Java\u300f\u96f6 - 0. \u8d77\u6b65.md": {"last_commit_date": "2023-08-20", "authors": []}, "docs/blog/posts/Coding/Java/\u300e\u4eceC\u5230Java\u300f\u96f6 - 1. \u90a3\u4e9b\u548cC\u633a\u50cf\u7684.md": {"last_commit_date": "2023-08-20", "authors": []}, "docs/blog/posts/Coding/Java/\u300e\u4eceC\u5230Java\u300f\u96f6 - 2. \u5b8c\u5168\u4e0d\u4e00\u6837\u7684\u201c\u5bf9\u8c61\u201d\u548c\u201c\u7c7b\u201d.md": {"last_commit_date": "2023-08-20", "authors": []}, "docs/blog/posts/Coding/Java/\u300e\u4eceC\u5230Java\u300f\u96f6 - 3. \u521d\u89c1\u5305\u4e0e\u8bbf\u95ee\u63a7\u5236\u4fee\u9970\u7b26.md": {"last_commit_date": "2023-08-20", "authors": []}, "docs/blog/posts/Coding/OI/\u9898\u89e3/BJTU-2021\u5c4a\u65b0\u751f\u5bd2\u8bad STL\u4e13\u9898.md": {"last_commit_date": "2023-08-14", "authors": []}, "docs/blog/posts/Coding/OI/\u9898\u89e3/CF1201C Maximum Median.md": {"last_commit_date": "2023-08-14", "authors": []}, "docs/blog/posts/Coding/OI/\u9898\u89e3/CF1223C Save the Nature.md": {"last_commit_date": "2023-08-14", "authors": []}, "docs/blog/posts/Coding/OI/\u9898\u89e3/CF1650F Vitaly and Advanced Useless Algorithms.md": {"last_commit_date": "2023-08-14", "authors": []}, "docs/blog/posts/Coding/OI/\u9898\u89e3/CF19B Checkout Assistant.md": {"last_commit_date": "2023-08-14", "authors": []}, "docs/blog/posts/Coding/OI/\u9898\u89e3/CF939E Maximize!.md": {"last_commit_date": "2023-08-14", "authors": []}, "docs/blog/posts/Coding/OI/\u9898\u89e3/P1182 \u6570\u5217\u5206\u6bb5 Section II.md": {"last_commit_date": "2023-08-14", "authors": []}, "docs/blog/posts/Coding/OI/\u9898\u89e3/P1873\u3010COCI 2011+2012 5\u3011EKO \u780d\u6811.md": {"last_commit_date": "2023-08-14", "authors": []}, "docs/blog/posts/Coding/OI/\u9898\u89e3/P2324 [SCOI2005]\u9a91\u58eb\u7cbe\u795e.md": {"last_commit_date": "2023-08-14", "authors": []}, "docs/blog/posts/Coding/OI/\u9898\u89e3/P2508 [HAOI2008]\u5706\u4e0a\u7684\u6574\u70b9.md": {"last_commit_date": "2023-08-14", "authors": []}, "docs/blog/posts/Coding/OI/\u9898\u89e3/P3799 \u5996\u68a6\u62fc\u6728\u68d2.md": {"last_commit_date": "2023-08-14", "authors": []}, "docs/blog/posts/Coding/Python/Python \u722c\u866b\u5165\u95e8.md": {"last_commit_date": "2023-08-20", "authors": []}, "docs/blog/posts/Coding/Python/Python\u57fa\u7840/\u300ePython\u57fa\u7840\u300f1. \u8d77\u6b65.md": {"last_commit_date": "2023-08-20", "authors": []}, "docs/blog/posts/Coding/Python/Python\u57fa\u7840/\u300ePython\u57fa\u7840\u300f2. \u57fa\u7840\u6570\u636e\u7c7b\u578b\u4e0e\u8fd0\u7b97.md": {"last_commit_date": "2023-12-19", "authors": []}, "docs/blog/posts/Coding/Python/Python\u57fa\u7840/\u300ePython\u57fa\u7840\u300f3. \u53d8\u91cf.md": {"last_commit_date": "2023-08-20", "authors": []}, "docs/blog/posts/Coding/Python/Python\u57fa\u7840/\u300ePython\u57fa\u7840\u300f4. \u5206\u652f\uff08if\uff09\u4e0e\u5faa\u73af\uff08while\uff09.md": {"last_commit_date": "2023-08-20", "authors": []}, "docs/blog/posts/Coding/Rust/\u6240\u6709\u6743 1 \u6240\u6709\u8005\u3001\u79fb\u52a8\u3001\u514b\u9686.md": {"last_commit_date": "2023-09-11", "authors": []}, "docs/blog/posts/Coding/Rust/\u6240\u6709\u6743 2 \u5f15\u7528\u4e0e\u501f\u7528.md": {"last_commit_date": "2023-08-20", "authors": []}, "docs/blog/posts/Linux/\u8bb0\u4e00\u6b21Manjaro KDE\u7f8e\u5316.md": {"last_commit_date": "2023-11-30", "authors": []}, "docs/blog/posts/Linux/NixOS/Nix Pills\u7b14\u8bb0/\u7b2c12\u7ae0 Inputs \u8bbe\u8ba1\u6a21\u5f0f.md": {"last_commit_date": "2023-08-20", "authors": []}, "docs/blog/posts/Linux/NixOS/Nix Pills\u7b14\u8bb0/\u7b2c6~7\u7ae0 Derivation.md": {"last_commit_date": "2023-08-20", "authors": []}, "docs/blog/posts/Mac/Yabai \u7a97\u53e3\u7ba1\u7406\u5668.md": {"last_commit_date": "2023-11-30", "authors": []}, "docs/blog/posts/Minecraft/NBT\u683c\u5f0f.md": {"last_commit_date": "2023-08-20", "authors": []}, "docs/blog/posts/git/Git \u539f\u7406.md": {"last_commit_date": "2023-08-20", "authors": []}, "docs/blog/posts/git/_\u5206\u652f.md": {"last_commit_date": "2023-08-20", "authors": []}, "docs/blog/posts/git/\u300egit\u300f0. \u6982\u8ff0.md": {"last_commit_date": "2023-08-20", "authors": []}, "docs/blog/posts/git/\u300egit\u300f1. \u4ed3\u5e93.md": {"last_commit_date": "2023-08-20", "authors": []}, "docs/blog/posts/git/\u300egit\u300f2. \u8bb0\u5f55\u66f4\u65b0.md": {"last_commit_date": "2023-08-20", "authors": []}, "docs/blog/posts/\u5b66\u6821\u7b14\u8bb0/CS143 Compiler \u7b14\u8bb0/-04-01-lexical-specification.md": {"last_commit_date": "2023-08-20", "authors": []}, "docs/blog/posts/\u5b66\u6821\u7b14\u8bb0/CS143 Compiler \u7b14\u8bb0/-04-02-finite-automata.md": {"last_commit_date": "2023-08-20", "authors": []}, "docs/blog/posts/\u5b66\u6821\u7b14\u8bb0/CS143 Compiler \u7b14\u8bb0/-04-03-regular-expressions-into-NFAs.md": {"last_commit_date": "2023-08-20", "authors": []}, "docs/blog/posts/\u5b66\u6821\u7b14\u8bb0/CS143 Compiler \u7b14\u8bb0/-04-04-NFA-to-DFA.md": {"last_commit_date": "2023-08-20", "authors": []}, "docs/blog/posts/\u5b66\u6821\u7b14\u8bb0/CS143 Compiler \u7b14\u8bb0/-PA1.md": {"last_commit_date": "2023-08-20", "authors": []}, "docs/blog/posts/\u5b66\u6821\u7b14\u8bb0/CS143 Compiler \u7b14\u8bb0/-SQL\u89e3\u6790.md": {"last_commit_date": "2023-08-20", "authors": []}, "docs/blog/posts/\u5b66\u6821\u7b14\u8bb0/CS143 Compiler \u7b14\u8bb0/-Week 1 01-02-structure-of-a-compiler-final.md": {"last_commit_date": "2023-08-20", "authors": []}, "docs/blog/posts/\u5b66\u6821\u7b14\u8bb0/CS143 Compiler \u7b14\u8bb0/-Week 1 02-01-cool-overview-final.md": {"last_commit_date": "2023-08-20", "authors": []}, "docs/blog/posts/\u5b66\u6821\u7b14\u8bb0/CS143 Compiler \u7b14\u8bb0/-Week 1 02-02-cool-example-ii-final.md": {"last_commit_date": "2023-08-20", "authors": []}, "docs/blog/posts/\u5b66\u6821\u7b14\u8bb0/CS143 Compiler \u7b14\u8bb0/-Week 1 02-03-cool-example-iii-final-correction.md": {"last_commit_date": "2023-08-20", "authors": []}, "docs/blog/posts/\u5b66\u6821\u7b14\u8bb0/CS143 Compiler \u7b14\u8bb0/-Week 2 03-01-lexical-analysis.md": {"last_commit_date": "2023-08-20", "authors": []}, "docs/blog/posts/\u5b66\u6821\u7b14\u8bb0/CS143 Compiler \u7b14\u8bb0/-Week 2 03-02-lexical-analysis-examples.md": {"last_commit_date": "2023-08-20", "authors": []}, "docs/blog/posts/\u5b66\u6821\u7b14\u8bb0/CS143 Compiler \u7b14\u8bb0/-Week 2 03-03-regular-languages-part-1.md": {"last_commit_date": "2023-08-20", "authors": []}, "docs/blog/posts/\u5b66\u6821\u7b14\u8bb0/CS143 Compiler \u7b14\u8bb0/-Week 2 03-04-formal-languages.md": {"last_commit_date": "2023-08-20", "authors": []}, "docs/blog/posts/\u5b66\u6821\u7b14\u8bb0/CS143 Compiler \u7b14\u8bb0/-Week 2 03-05-lexical-specifications.md": {"last_commit_date": "2023-08-20", "authors": []}, "docs/blog/posts/\u5b66\u6821\u7b14\u8bb0/CS143 Compiler \u7b14\u8bb0/-\u5f62\u5f0f\u8bed\u8a00\u3001\u81ea\u52a8\u673a\u4e0e\u6b63\u5219\u8868\u8fbe\u5f0f.md": {"last_commit_date": "2023-08-20", "authors": []}, "docs/blog/posts/\u5b66\u6821\u7b14\u8bb0/CS143 Compiler \u7b14\u8bb0/-\u7f16\u8bd1\u539f\u7406 2. \u8bed\u6cd5\u5206\u6790 - bison.md": {"last_commit_date": "2023-08-20", "authors": []}, "docs/blog/posts/\u5b66\u6821\u7b14\u8bb0/CS143 Compiler \u7b14\u8bb0/CS143 \u8bfe\u7a0b\u76f8\u5173\u8d44\u6599\u53ca\u73af\u5883\u642d\u5efa.md": {"last_commit_date": "2023-08-20", "authors": []}, "docs/blog/posts/\u5b66\u6821\u7b14\u8bb0/CS143 Compiler \u7b14\u8bb0/\u5b9e\u8badII \u2014\u2014 SQL\u89e3\u6790 Draft.md": {"last_commit_date": "2023-08-20", "authors": []}, "docs/blog/posts/\u5b66\u6821\u7b14\u8bb0/CS143 Compiler \u7b14\u8bb0/\u7f16\u8bd1\u539f\u7406 0. \u6982\u8ff0.md": {"last_commit_date": "2023-08-20", "authors": []}, "docs/blog/posts/\u5b66\u6821\u7b14\u8bb0/CS143 Compiler \u7b14\u8bb0/\u7f16\u8bd1\u539f\u7406 1. \u8bcd\u6cd5\u5206\u6790 - flex.md": {"last_commit_date": "2023-08-20", "authors": []}, "docs/blog/posts/\u5b66\u6821\u7b14\u8bb0/PostgreSQL/Debian\u670d\u52a1\u5668\u914d\u7f6ePostgresql\u8fdc\u7a0b\u8bbf\u95ee.md": {"last_commit_date": "2023-08-20", "authors": []}, "docs/blog/posts/\u5b66\u6821\u7b14\u8bb0/PostgreSQL/PostgreSQL Data Defination.md": {"last_commit_date": "2023-08-20", "authors": []}, "docs/blog/posts/\u5b66\u6821\u7b14\u8bb0/PostgreSQL/PostgreSQL Data Manipulation.md": {"last_commit_date": "2023-08-20", "authors": []}, "docs/blog/posts/\u5b66\u6821\u7b14\u8bb0/PostgreSQL/PostgreSQL PL_pgSQL.md": {"last_commit_date": "2023-08-20", "authors": []}, "docs/blog/posts/\u5b66\u6821\u7b14\u8bb0/PostgreSQL/PostgreSQL Views.md": {"last_commit_date": "2023-08-20", "authors": []}, "docs/blog/posts/\u5b66\u6821\u7b14\u8bb0/PostgreSQL/PostgreSQL \u4e00\u3001\u521b\u5efa\u3001\u5220\u9664\u8868.md": {"last_commit_date": "2023-08-20", "authors": []}, "docs/blog/posts/\u5b66\u6821\u7b14\u8bb0/PostgreSQL/PostgreSQL \u7d22\u5f15.md": {"last_commit_date": "2023-08-20", "authors": []}, "docs/blog/posts/\u5b66\u6821\u7b14\u8bb0/PostgreSQL/PostgreSQL\u5b89\u88c5.md": {"last_commit_date": "2023-08-20", "authors": []}, "docs/blog/posts/\u5b66\u6821\u7b14\u8bb0/PostgreSQL/_PostgreSQL Trigger.md": {"last_commit_date": "2023-08-20", "authors": []}, "docs/blog/posts/\u5b66\u6821\u7b14\u8bb0/PostgreSQL/\u4e13\u4e1a\u8bfe\u7a0b\u7efc\u5408\u5b9e\u8badII \u8bb0\u5f55-\u4e13\u9898\u4e00\u3001\u4e8c.md": {"last_commit_date": "2023-08-20", "authors": []}, "docs/blog/posts/\u5b66\u6821\u7b14\u8bb0/\u4eba\u5de5\u667a\u80fd\u57fa\u7840/\u73af\u5883\u914d\u7f6e.md": {"last_commit_date": "2023-08-20", "authors": []}, "docs/blog/posts/\u5b66\u6821\u7b14\u8bb0/\u4eba\u5de5\u667a\u80fd\u57fa\u7840/\u914d\u7f6e paddlepaddle-gpu.md": {"last_commit_date": "2023-08-20", "authors": []}, "docs/blog/posts/\u5b66\u6821\u7b14\u8bb0/\u4eba\u5de5\u667a\u80fd\u57fa\u7840/\u9879\u76ee\u8981\u6c42.md": {"last_commit_date": "2023-08-20", "authors": []}, "docs/blog/posts/\u5b66\u6821\u7b14\u8bb0/\u7b97\u6cd5\u8bbe\u8ba1\u4e0e\u5206\u6790/4. \u52a8\u6001\u89c4\u5212.md": {"last_commit_date": "2023-08-20", "authors": []}, "docs/nix/index.md": {"last_commit_date": "2024-01-24", "authors": []}, "docs/nix/1.md": {"last_commit_date": "2024-01-24", "authors": []}, "docs/notes/index.md": {"last_commit_date": "2024-01-01", "authors": []}, "docs/notes/ComputerNetwork/Internet Protocol.md": {"last_commit_date": "2023-11-14", "authors": []}, "docs/notes/ComputerNetwork/Transmission Control Protocol.md": {"last_commit_date": "2023-12-05", "authors": []}, "docs/notes/ComputerNetwork/traceroute.md": {"last_commit_date": "2023-11-14", "authors": []}, "docs/notes/DigitalImageProcessing/fourier-transform.md": {"last_commit_date": "2024-06-20", "authors": []}, "docs/notes/MachineLearning/decision_tree.md": {"last_commit_date": "2023-11-18", "authors": []}, "docs/notes/MachineLearning/naive_bayes_classifier.md": {"last_commit_date": "2024-01-08", "authors": []}, "docs/notes/MachineLearning/pca.md": {"last_commit_date": "2024-01-08", "authors": []}, "docs/notes/OperatingSystem/cpu-scheduling.md": {"last_commit_date": "2024-01-07", "authors": []}, "docs/notes/OperatingSystem/deadlock.md": {"last_commit_date": "2024-01-07", "authors": []}, "docs/notes/OperatingSystem/disk-scheduling.md": {"last_commit_date": "2024-01-04", "authors": []}, "docs/notes/OperatingSystem/intro.md": {"last_commit_date": "2024-01-07", "authors": []}, "docs/notes/OperatingSystem/main-memory.md": {"last_commit_date": "2023-12-25", "authors": []}, "docs/notes/OperatingSystem/process-synchronization.md": {"last_commit_date": "2024-01-07", "authors": []}, "docs/notes/OperatingSystem/processes.md": {"last_commit_date": "2024-01-07", "authors": []}, "docs/notes/OperatingSystem/review.md": {"last_commit_date": "2024-01-04", "authors": []}, "docs/notes/OperatingSystem/threads.md": {"last_commit_date": "2024-01-07", "authors": []}, "docs/notes/OperatingSystem/virtual-memory.md": {"last_commit_date": "2024-01-07", "authors": []}, "docs/notes/ProjectManagement/critical-path-methodology.md": {"last_commit_date": "2024-01-01", "authors": []}, "docs/notes/ProjectManagement/earned-value-analysis.md": {"last_commit_date": "2024-01-03", "authors": []}, "docs/notes/SoftwareTesting/black-box.md": {"last_commit_date": "2024-01-10", "authors": []}, "docs/notes/SoftwareTesting/final-exam.md": {"last_commit_date": "2024-01-10", "authors": []}}}